<?xml version="1.0" encoding="UTF-8"?>
<objects serializationModel="Studio.01.10.00">
    <object class="Event" id="{aec1aae8-f426-4e69-912d-931d47464e84}">
        <property name="name">
            <value>2.2</value>
        </property>
        <property name="outputFormat">
            <value>1</value>
        </property>
        <relationship name="folder">
            <destination>{c261405c-6b68-435f-8f25-f54af5897724}</destination>
        </relationship>
        <relationship name="mixer">
            <destination>{c3325bf5-055b-4a2a-a268-23e7a7f51b5e}</destination>
        </relationship>
        <relationship name="masterTrack">
            <destination>{d9cc3835-e5b5-4ac9-bcbe-5a0ad9497f5e}</destination>
        </relationship>
        <relationship name="mixerInput">
            <destination>{4e5c2c9b-95d7-47e6-aba5-8c3be01108d7}</destination>
        </relationship>
        <relationship name="automatableProperties">
            <destination>{c8d8fc82-6678-4621-9230-73dfa4771556}</destination>
        </relationship>
        <relationship name="markerTracks">
            <destination>{77931325-53d1-45bd-b5e8-6bf7afdafa0a}</destination>
        </relationship>
        <relationship name="groupTracks">
            <destination>{ff155f3a-c756-4f43-a154-9aebdeed6fb6}</destination>
        </relationship>
        <relationship name="timeline">
            <destination>{b79e4340-6059-4f3c-b4ea-ea2ab51aff6d}</destination>
        </relationship>
        <relationship name="banks">
            <destination>{331392c8-587d-4ab7-a57c-10aed11b5e54}</destination>
        </relationship>
    </object>
    <object class="EventMixer" id="{c3325bf5-055b-4a2a-a268-23e7a7f51b5e}">
        <relationship name="masterBus">
            <destination>{e79ce2ce-9dad-469c-8fa7-c3842cc401fd}</destination>
        </relationship>
    </object>
    <object class="MasterTrack" id="{d9cc3835-e5b5-4ac9-bcbe-5a0ad9497f5e}">
        <relationship name="mixerGroup">
            <destination>{e79ce2ce-9dad-469c-8fa7-c3842cc401fd}</destination>
        </relationship>
    </object>
    <object class="MixerInput" id="{4e5c2c9b-95d7-47e6-aba5-8c3be01108d7}">
        <relationship name="effectChain">
            <destination>{94eb123b-5a5e-4277-95c2-9dc4083a86f1}</destination>
        </relationship>
        <relationship name="panner">
            <destination>{6411ae40-bbcd-448f-b4a1-fa1d7dcf060d}</destination>
        </relationship>
        <relationship name="output">
            <destination>{891f9ff5-36a0-41db-92ba-ae3e68985b4a}</destination>
        </relationship>
    </object>
    <object class="EventAutomatableProperties" id="{c8d8fc82-6678-4621-9230-73dfa4771556}"/>
    <object class="MarkerTrack" id="{77931325-53d1-45bd-b5e8-6bf7afdafa0a}"/>
    <object class="GroupTrack" id="{ff155f3a-c756-4f43-a154-9aebdeed6fb6}">
        <relationship name="modules">
            <destination>{ff4e9506-a26b-49e2-952e-075a05092c0f}</destination>
        </relationship>
        <relationship name="mixerGroup">
            <destination>{3eec325d-8224-4d49-91b2-cb15a33ef835}</destination>
        </relationship>
    </object>
    <object class="Timeline" id="{b79e4340-6059-4f3c-b4ea-ea2ab51aff6d}">
        <relationship name="modules">
            <destination>{ff4e9506-a26b-49e2-952e-075a05092c0f}</destination>
        </relationship>
    </object>
    <object class="EventMixerMaster" id="{e79ce2ce-9dad-469c-8fa7-c3842cc401fd}">
        <relationship name="effectChain">
            <destination>{0468ae4e-feec-4adb-97f5-0ada1d12def7}</destination>
        </relationship>
        <relationship name="panner">
            <destination>{b0e72798-2f0e-49cd-aa91-9f92cdf134e5}</destination>
        </relationship>
        <relationship name="mixer">
            <destination>{c3325bf5-055b-4a2a-a268-23e7a7f51b5e}</destination>
        </relationship>
    </object>
    <object class="MixerBusEffectChain" id="{94eb123b-5a5e-4277-95c2-9dc4083a86f1}">
        <relationship name="effects">
            <destination>{d6b303d4-1fe3-4984-9e92-e213135b6676}</destination>
        </relationship>
    </object>
    <object class="MixerBusPanner" id="{6411ae40-bbcd-448f-b4a1-fa1d7dcf060d}"/>
    <object class="SingleSound" id="{ff4e9506-a26b-49e2-952e-075a05092c0f}">
        <property name="length">
            <value>11</value>
        </property>
        <relationship name="audioFile">
            <destination>{f5ddd9ec-88aa-437a-a814-56ab8f1707e0}</destination>
        </relationship>
    </object>
    <object class="EventMixerGroup" id="{3eec325d-8224-4d49-91b2-cb15a33ef835}">
        <property name="volume">
            <value>-15</value>
        </property>
        <property name="name">
            <value>Audio 1</value>
        </property>
        <relationship name="effectChain">
            <destination>{dfa762ad-80e2-41ea-95d2-985400ce7412}</destination>
        </relationship>
        <relationship name="panner">
            <destination>{b1e48eed-bc70-45ec-aed0-296f19bff235}</destination>
        </relationship>
        <relationship name="output">
            <destination>{e79ce2ce-9dad-469c-8fa7-c3842cc401fd}</destination>
        </relationship>
    </object>
    <object class="MixerBusEffectChain" id="{0468ae4e-feec-4adb-97f5-0ada1d12def7}">
        <relationship name="effects">
            <destination>{83f32552-f26d-4bea-8b8a-3932413e3db9}</destination>
        </relationship>
    </object>
    <object class="MixerBusPanner" id="{b0e72798-2f0e-49cd-aa91-9f92cdf134e5}"/>
    <object class="MixerBusFader" id="{d6b303d4-1fe3-4984-9e92-e213135b6676}"/>
    <object class="MixerBusEffectChain" id="{dfa762ad-80e2-41ea-95d2-985400ce7412}">
        <relationship name="effects">
            <destination>{6764a0dc-863b-427e-a68a-1f4c7e2151b9}</destination>
        </relationship>
    </object>
    <object class="MixerBusPanner" id="{b1e48eed-bc70-45ec-aed0-296f19bff235}"/>
    <object class="MixerBusFader" id="{83f32552-f26d-4bea-8b8a-3932413e3db9}"/>
    <object class="MixerBusFader" id="{6764a0dc-863b-427e-a68a-1f4c7e2151b9}"/>
</objects>
